mcp_grafana/__init__.py
mcp_grafana/cli.py
mcp_grafana/client.py
mcp_grafana/grafana_types.py
mcp_grafana/py.typed
mcp_grafana/settings.py
mcp_grafana/tools/__init__.py
mcp_grafana/tools/datasources.py
mcp_grafana/tools/incident.py
mcp_grafana/tools/prometheus.py
mcp_grafana/tools/search.py
mcp_grafana-0.1.1.dist-info/METADATA
mcp_grafana-0.1.1.dist-info/WHEEL
mcp_grafana-0.1.1.dist-info/entry_points.txt
mcp_grafana-0.1.1.dist-info/licenses/LICENSE
mcp_grafana-0.1.1.dist-info/RECORD
