Metadata-Version: 2.4
Name: mcp-grafana
Version: 0.1.1
Summary: MCP server for Grafana and the ecosystem
Author-email: Ben Sully <ben.sully@grafana.com>
License:                                  Apache License
License-File: LICENSE
Requires-Python: >=3.10
Requires-Dist: httpx>=0.28.1
Requires-Dist: mcp[cli]==1.2.0
Requires-Dist: pydantic-settings>=2.7.0
Requires-Dist: pydantic>=2.10.4
Requires-Dist: typer>=0.15.1
